[{"label":"Phase 1: Hierarchical Proposal","upper_level":{"label":"Upper Level \u2014 Supergraph G\u00b2","phase2":{"label":"Phase 2: Recursive Partitioning","tree_cuts":[{"label":"Phase 3: Tree Cut 1","level":"supergraph","edges":[["1","33"],["21","35"],["21","34"],["21","29"],["21","27"],["31","3"],["31","20"],["32","29"],["33","29"],["35","20"],["28","34"],["20","36"]],"root":"31","cut_node":"21","psi_chosen":6.0,"psi_total":28.0,"n_cuts":8,"node_feasibility":{"1":{"demand_ok":true,"compl_demand_ok":false,"has_facility":true,"compl_facility":true,"demand":850},"21":{"demand_ok":false,"compl_demand_ok":false,"has_facility":true,"compl_facility":true,"demand":13550},"31":{"demand_ok":false,"compl_demand_ok":false,"has_facility":true,"compl_facility":true,"demand":20000},"32":{"demand_ok":true,"compl_demand_ok":false,"has_facility":true,"compl_facility":true,"demand":1100},"33":{"demand_ok":true,"compl_demand_ok":false,"has_facility":true,"compl_facility":true,"demand":2000},"3":{"demand_ok":true,"compl_demand_ok":false,"has_facility":true,"compl_facility":true,"demand":1050},"35":{"demand_ok":false,"compl_demand_ok":true,"has_facility":true,"compl_facility":true,"demand":14750},"27":{"demand_ok":true,"compl_demand_ok":false,"has_facility":true,"compl_facility":true,"demand":3250},"28":{"demand_ok":true,"compl_demand_ok":false,"has_facility":true,"compl_facility":true,"demand":850},"20":{"demand_ok":false,"compl_demand_ok":true,"has_facility":true,"compl_facility":true,"demand":18000},"36":{"demand_ok":true,"compl_demand_ok":false,"has_facility":true,"compl_facility":true,"demand":2200},"34":{"demand_ok":false,"compl_demand_ok":false,"has_facility":true,"compl_facility":true,"demand":2650},"29":{"demand_ok":true,"compl_demand_ok":false,"has_facility":true,"compl_facility":true,"demand":5000}},"extracted_nodes":["35","3","36","20","31"]},{"label":"Phase 3: Tree Cut 2","level":"supergraph","edges":[["1","32"],["21","32"],["21","27"],["32","33"],["32","29"],["28","34"],["34","29"]],"root":"34","cut_node":"32","psi_chosen":5.0,"psi_total":17.0,"n_cuts":4,"node_feasibility":{"1":{"demand_ok":true,"compl_demand_ok":false,"has_facility":true,"compl_facility":true,"demand":850},"21":{"demand_ok":true,"compl_demand_ok":false,"has_facility":true,"compl_facility":true,"demand":5900},"32":{"demand_ok":false,"compl_demand_ok":false,"has_facility":true,"compl_facility":true,"demand":9000},"33":{"demand_ok":true,"compl_demand_ok":false,"has_facility":true,"compl_facility":true,"demand":1150},"27":{"demand_ok":true,"compl_demand_ok":false,"has_facility":true,"compl_facility":true,"demand":3250},"28":{"demand_ok":true,"compl_demand_ok":false,"has_facility":true,"compl_facility":true,"demand":850},"34":{"demand_ok":false,"compl_demand_ok":false,"has_facility":true,"compl_facility":true,"demand":13550},"29":{"demand_ok":false,"compl_demand_ok":false,"has_facility":true,"compl_facility":true,"demand":10900}},"extracted_nodes":["34","28","29"]},{"label":"Phase 3: Tree Cut 3","level":"supergraph","edges":[["32","33"],["32","21"],["1","33"],["21","27"]],"root":"21","cut_node":"27","psi_chosen":3.0,"psi_total":8.0,"n_cuts":3,"node_feasibility":{"32":{"demand_ok":true,"compl_demand_ok":true,"has_facility":true,"compl_facility":true,"demand":3100},"1":{"demand_ok":true,"compl_demand_ok":false,"has_facility":true,"compl_facility":true,"demand":850},"33":{"demand_ok":true,"compl_demand_ok":false,"has_facility":true,"compl_facility":true,"demand":2000},"21":{"demand_ok":false,"compl_demand_ok":false,"has_facility":true,"compl_facility":true,"demand":9000},"27":{"demand_ok":true,"compl_demand_ok":true,"has_facility":true,"compl_facility":true,"demand":3250}},"extracted_nodes":["27"]},{"label":"Phase 3: Tree Cut 4","level":"supergraph","edges":[["32","1"],["32","21"],["32","33"]],"root":"32","cut_node":"32","psi_chosen":6.0,"psi_total":9.0,"n_cuts":2,"node_feasibility":{"32":{"demand_ok":true,"compl_demand_ok":false,"has_facility":true,"compl_facility":true,"demand":5750},"1":{"demand_ok":true,"compl_demand_ok":true,"has_facility":true,"compl_facility":true,"demand":850},"21":{"demand_ok":false,"compl_demand_ok":true,"has_facility":true,"compl_facility":true,"demand":2650},"33":{"demand_ok":true,"compl_demand_ok":false,"has_facility":true,"compl_facility":true,"demand":1150}},"extracted_nodes":["32","33","21","1"]}]},"phase4":{"label":"Phase 4: Level-2 Facility Assignment","centers":{"1":"(17, 19)","3":"(3, 15)","4":"(4, 5)","5":"(12, 10)","2":"(15, 2)"}},"supergraph_coords":{"1":[13.764705882352942,15.882352941176471],"3":[14.095238095238095,18.333333333333332],"20":[5.904761904761905,17.19047619047619],"21":[12.49056603773585,7.584905660377358],"27":[4.769230769230769,6.123076923076923],"28":[1.6470588235294117,1.411764705882353],"29":[17.44736842105263,3.8421052631578947],"31":[9.368421052631579,15.0],"32":[15.136363636363637,10.954545454545455],"33":[18.0,14.130434782608695],"34":[9.083333333333334,1.3888888888888888],"35":[6.416666666666667,11.5],"36":[1.75,14.477272727272727]}},"select":{"label":"Select Superdistrict D\u00b2","selected_superdistricts":["34","28","29"],"merged_base_nodes":["(12, 1)","(4, 0)","(9, 2)","(5, 1)","(8, 0)","(17, 3)","(19, 0)","(19, 9)","(2, 2)","(1, 0)","(7, 4)","(6, 2)","(18, 4)","(7, 1)","(18, 1)","(18, 10)","(14, 0)","(3, 0)","(17, 5)","(8, 2)","(19, 2)","(9, 1)","(19, 8)","(2, 4)","(1, 2)","(2, 1)","(13, 1)","(16, 0)","(7, 3)","(18, 3)","(14, 2)","(4, 1)","(8, 4)","(19, 4)","(9, 3)","(8, 1)","(11, 0)","(0, 0)","(19, 1)","(19, 10)","(2, 3)","(16, 2)","(15, 0)","(18, 5)","(6, 3)","(14, 1)","(3, 1)","(17, 0)","(19, 6)","(17, 6)","(11, 2)","(10, 0)","(8, 3)","(0, 2)","(19, 3)","(1, 3)","(16, 4)","(15, 2)","(16, 1)","(18, 7)","(12, 0)","(5, 0)","(17, 2)","(19, 5)","(10, 2)","(9, 4)","(11, 1)","(0, 1)","(6, 1)","(16, 3)","(7, 0)","(15, 1)","(18, 0)","(18, 9)","(18, 6)","(12, 2)","(5, 2)","(17, 4)","(9, 0)","(17, 1)","(19, 7)","(1, 1)","(0, 3)","(10, 1)","(13, 0)","(2, 0)","(16, 5)","(7, 2)","(6, 0)","(18, 2)","(15, 3)"],"supergraph_nodes":{"1":{"demand":850,"teams":1},"21":{"demand":2650,"teams":3},"31":{"demand":950,"teams":1},"32":{"demand":1100,"teams":1},"33":{"demand":1150,"teams":1},"3":{"demand":1050,"teams":1},"35":{"demand":1200,"teams":1},"27":{"demand":3250,"teams":3},"28":{"demand":850,"teams":1},"20":{"demand":1050,"teams":1},"36":{"demand":2200,"teams":2},"34":{"demand":1800,"teams":2},"29":{"demand":1900,"teams":2}},"supergraph_coords":{"1":[13.764705882352942,15.882352941176471],"21":[12.49056603773585,7.584905660377358],"31":[9.368421052631579,15.0],"32":[15.136363636363637,10.954545454545455],"33":[18.0,14.130434782608695],"3":[14.095238095238095,18.333333333333332],"35":[6.416666666666667,11.5],"27":[4.769230769230769,6.123076923076923],"28":[1.6470588235294117,1.411764705882353],"20":[5.904761904761905,17.19047619047619],"36":[1.75,14.477272727272727],"34":[9.083333333333334,1.3888888888888888],"29":[17.44736842105263,3.8421052631578947]},"supergraph_edges":[["1","31"],["1","33"],["1","3"],["1","32"],["21","31"],["21","32"],["21","35"],["21","27"],["21","29"],["21","34"],["31","32"],["31","3"],["31","35"],["31","20"],["32","33"],["32","29"],["33","3"],["33","29"],["3","20"],["35","27"],["35","20"],["35","36"],["27","28"],["27","36"],["27","34"],["28","34"],["20","36"],["34","29"]]},"lower_level":{"label":"Lower Level \u2014 Base Graph H","phase2":{"label":"Phase 2: Recursive Partitioning","tree_cuts":[{"label":"Phase 3: Tree Cut 1","level":"base","edges":[["(4, 0)","(5, 0)"],["(4, 0)","(4, 1)"],["(5, 1)","(5, 2)"],["(5, 1)","(5, 0)"],["(17, 3)","(16, 3)"],["(17, 3)","(17, 4)"],["(8, 0)","(9, 0)"],["(8, 0)","(7, 0)"],["(8, 0)","(8, 1)"],["(19, 0)","(19, 1)"],["(19, 9)","(19, 8)"],["(19, 9)","(18, 9)"],["(19, 9)","(19, 10)"],["(2, 2)","(2, 1)"],["(2, 2)","(1, 2)"],["(2, 2)","(2, 3)"],["(6, 2)","(6, 3)"],["(6, 2)","(5, 2)"],["(7, 1)","(8, 1)"],["(7, 1)","(6, 1)"],["(7, 1)","(7, 2)"],["(18, 1)","(17, 1)"],["(18, 1)","(19, 1)"],["(18, 10)","(18, 9)"],["(17, 5)","(16, 5)"],["(17, 5)","(18, 5)"],["(17, 5)","(17, 6)"],["(8, 2)","(9, 2)"],["(8, 2)","(8, 3)"],["(19, 2)","(18, 2)"],["(9, 1)","(9, 2)"],["(9, 1)","(9, 0)"],["(9, 1)","(10, 1)"],["(2, 4)","(2, 3)"],["(13, 1)","(13, 0)"],["(13, 1)","(12, 1)"],["(7, 3)","(8, 3)"],["(7, 3)","(7, 4)"],["(7, 3)","(6, 3)"],["(18, 3)","(18, 4)"],["(18, 3)","(18, 2)"],["(8, 4)","(8, 3)"],["(8, 4)","(9, 4)"],["(19, 4)","(19, 5)"],["(19, 4)","(18, 4)"],["(19, 4)","(19, 3)"],["(9, 3)","(9, 4)"],["(11, 0)","(10, 0)"],["(11, 0)","(11, 1)"],["(0, 0)","(1, 0)"],["(0, 0)","(0, 1)"],["(15, 0)","(16, 0)"],["(15, 0)","(14, 0)"],["(18, 5)","(19, 5)"],["(18, 5)","(18, 6)"],["(14, 1)","(15, 1)"],["(14, 1)","(14, 2)"],["(3, 1)","(4, 1)"],["(3, 1)","(2, 1)"],["(17, 0)","(17, 1)"],["(17, 0)","(18, 0)"],["(17, 0)","(16, 0)"],["(19, 6)","(19, 5)"],["(19, 6)","(19, 7)"],["(11, 2)","(12, 2)"],["(11, 2)","(10, 2)"],["(0, 2)","(1, 2)"],["(0, 2)","(0, 3)"],["(1, 3)","(2, 3)"],["(15, 2)","(14, 2)"],["(15, 2)","(16, 2)"],["(15, 2)","(15, 3)"],["(16, 1)","(16, 0)"],["(16, 1)","(15, 1)"],["(18, 7)","(18, 6)"],["(17, 2)","(17, 1)"],["(16, 3)","(16, 2)"],["(7, 0)","(6, 0)"],["(17, 4)","(16, 4)"],["(9, 0)","(10, 0)"],["(13, 0)","(14, 0)"],["(16, 5)","(16, 4)"],["(12, 1)","(12, 0)"],["(12, 1)","(12, 2)"],["(9, 2)","(10, 2)"],["(1, 0)","(2, 0)"],["(3, 0)","(2, 0)"],["(19, 8)","(19, 7)"],["(2, 1)","(1, 1)"],["(2, 1)","(2, 0)"]],"root":"(19, 7)","cut_node":"(14, 0)","psi_chosen":18.0,"psi_total":112.0,"n_cuts":15,"node_feasibility":{"(4, 0)":{"demand_ok":true,"compl_demand_ok":false,"has_facility":true,"compl_facility":true,"demand":850},"(5, 1)":{"demand_ok":true,"compl_demand_ok":false,"has_facility":true,"compl_facility":true,"demand":950},"(17, 3)":{"demand_ok":false,"compl_demand_ok":false,"has_facility":true,"compl_facility":true,"demand":3450},"(8, 0)":{"demand_ok":false,"compl_demand_ok":false,"has_facility":true,"compl_facility":true,"demand":350},"(19, 0)":{"demand_ok":false,"compl_demand_ok":false,"has_facility":false,"compl_facility":true,"demand":50},"(19, 9)":{"demand_ok":false,"compl_demand_ok":false,"has_facility":true,"compl_facility":true,"demand":200},"(2, 2)":{"demand_ok":false,"compl_demand_ok":false,"has_facility":true,"compl_facility":true,"demand":350},"(6, 2)":{"demand_ok":true,"compl_demand_ok":false,"has_facility":true,"compl_facility":true,"demand":1050},"(7, 1)":{"demand_ok":false,"compl_demand_ok":false,"has_facility":true,"compl_facility":true,"demand":150},"(18, 1)":{"demand_ok":false,"compl_demand_ok":false,"has_facility":true,"compl_facility":true,"demand":150},"(18, 10)":{"demand_ok":false,"compl_demand_ok":false,"has_facility":true,"compl_facility":true,"demand":50},"(17, 5)":{"demand_ok":false,"compl_demand_ok":true,"has_facility":true,"compl_facility":true,"demand":3700},"(8, 2)":{"demand_ok":false,"compl_demand_ok":false,"has_facility":true,"compl_facility":true,"demand":1450},"(19, 2)":{"demand_ok":false,"compl_demand_ok":false,"has_facility":true,"compl_facility":true,"demand":50},"(9, 1)":{"demand_ok":false,"compl_demand_ok":false,"has_facility":true,"compl_facility":true,"demand":650},"(2, 4)":{"demand_ok":false,"compl_demand_ok":false,"has_facility":true,"compl_facility":true,"demand":50},"(13, 1)":{"demand_ok":false,"compl_demand_ok":false,"has_facility":true,"compl_facility":true,"demand":2450},"(7, 3)":{"demand_ok":false,"compl_demand_ok":false,"has_facility":true,"compl_facility":true,"demand":1200},"(18, 3)":{"demand_ok":false,"compl_demand_ok":false,"has_facility":true,"compl_facility":true,"demand":150},"(8, 4)":{"demand_ok":false,"compl_demand_ok":false,"has_facility":true,"compl_facility":true,"demand":150},"(19, 4)":{"demand_ok":false,"compl_demand_ok":false,"has_facility":true,"compl_facility":true,"demand":300},"(9, 3)":{"demand_ok":false,"compl_demand_ok":false,"has_facility":false,"compl_facility":true,"demand":50},"(11, 0)":{"demand_ok":false,"compl_demand_ok":false,"has_facility":true,"compl_facility":true,"demand":100},"(0, 0)":{"demand_ok":false,"compl_demand_ok":false,"has_facility":false,"compl_facility":true,"demand":100},"(15, 0)":{"demand_ok":true,"compl_demand_ok":true,"has_facility":true,"compl_facility":true,"demand":2600},"(18, 5)":{"demand_ok":false,"compl_demand_ok":false,"has_facility":true,"compl_facility":true,"demand":3850},"(14, 1)":{"demand_ok":false,"compl_demand_ok":false,"has_facility":true,"compl_facility":true,"demand":3150},"(3, 1)":{"demand_ok":true,"compl_demand_ok":false,"has_facility":true,"compl_facility":true,"demand":750},"(17, 0)":{"demand_ok":false,"compl_demand_ok":false,"has_facility":true,"compl_facility":true,"demand":350},"(19, 6)":{"demand_ok":false,"compl_demand_ok":false,"has_facility":true,"compl_facility":true,"demand":4250},"(11, 2)":{"demand_ok":false,"compl_demand_ok":false,"has_facility":true,"compl_facility":true,"demand":2250},"(0, 2)":{"demand_ok":false,"compl_demand_ok":false,"has_facility":true,"compl_facility":true,"demand":100},"(1, 3)":{"demand_ok":false,"compl_demand_ok":false,"has_facility":true,"compl_facility":true,"demand":50},"(15, 2)":{"demand_ok":false,"compl_demand_ok":false,"has_facility":true,"compl_facility":true,"demand":3300},"(16, 1)":{"demand_ok":false,"compl_demand_ok":false,"has_facility":true,"compl_facility":true,"demand":3050},"(18, 7)":{"demand_ok":false,"compl_demand_ok":false,"has_facility":false,"compl_facility":true,"demand":50},"(5, 0)":{"demand_ok":true,"compl_demand_ok":false,"has_facility":true,"compl_facility":true,"demand":900},"(17, 2)":{"demand_ok":false,"compl_demand_ok":false,"has_facility":false,"compl_facility":true,"demand":50},"(6, 1)":{"demand_ok":false,"compl_demand_ok":false,"has_facility":false,"compl_facility":true,"demand":50},"(16, 3)":{"demand_ok":false,"compl_demand_ok":false,"has_facility":true,"compl_facility":true,"demand":3400},"(7, 0)":{"demand_ok":false,"compl_demand_ok":false,"has_facility":true,"compl_facility":true,"demand":100},"(18, 0)":{"demand_ok":false,"compl_demand_ok":false,"has_facility":false,"compl_facility":true,"demand":50},"(18, 9)":{"demand_ok":false,"compl_demand_ok":false,"has_facility":true,"compl_facility":true,"demand":100},"(5, 2)":{"demand_ok":true,"compl_demand_ok":false,"has_facility":true,"compl_facility":true,"demand":1000},"(17, 4)":{"demand_ok":false,"compl_demand_ok":true,"has_facility":true,"compl_facility":true,"demand":3500},"(9, 0)":{"demand_ok":false,"compl_demand_ok":false,"has_facility":true,"compl_facility":true,"demand":550},"(10, 1)":{"demand_ok":false,"compl_demand_ok":false,"has_facility":true,"compl_facility":true,"demand":50},"(13, 0)":{"demand_ok":false,"compl_demand_ok":false,"has_facility":true,"compl_facility":true,"demand":2500},"(16, 5)":{"demand_ok":false,"compl_demand_ok":true,"has_facility":true,"compl_facility":true,"demand":3600},"(7, 2)":{"demand_ok":false,"compl_demand_ok":false,"has_facility":true,"compl_facility":true,"demand":50},"(18, 2)":{"demand_ok":false,"compl_demand_ok":false,"has_facility":true,"compl_facility":true,"demand":100},"(12, 1)":{"demand_ok":false,"compl_demand_ok":false,"has_facility":true,"compl_facility":true,"demand":2400},"(9, 2)":{"demand_ok":false,"compl_demand_ok":false,"has_facility":true,"compl_facility":true,"demand":2150},"(1, 0)":{"demand_ok":false,"compl_demand_ok":false,"has_facility":false,"compl_facility":true,"demand":150},"(7, 4)":{"demand_ok":false,"compl_demand_ok":false,"has_facility":true,"compl_facility":true,"demand":50},"(18, 4)":{"demand_ok":false,"compl_demand_ok":false,"has_facility":true,"compl_facility":true,"demand":200},"(14, 0)":{"demand_ok":true,"compl_demand_ok":true,"has_facility":true,"compl_facility":true,"demand":2550},"(3, 0)":{"demand_ok":false,"compl_demand_ok":false,"has_facility":false,"compl_facility":true,"demand":50},"(19, 8)":{"demand_ok":false,"compl_demand_ok":false,"has_facility":true,"compl_facility":true,"demand":250},"(1, 2)":{"demand_ok":false,"compl_demand_ok":false,"has_facility":true,"compl_facility":true,"demand":150},"(2, 1)":{"demand_ok":false,"compl_demand_ok":false,"has_facility":true,"compl_facility":true,"demand":700},"(16, 0)":{"demand_ok":false,"compl_demand_ok":false,"has_facility":true,"compl_facility":true,"demand":3000},"(14, 2)":{"demand_ok":false,"compl_demand_ok":false,"has_facility":true,"compl_facility":true,"demand":3200},"(4, 1)":{"demand_ok":true,"compl_demand_ok":false,"has_facility":true,"compl_facility":true,"demand":800},"(8, 1)":{"demand_ok":false,"compl_demand_ok":false,"has_facility":true,"compl_facility":true,"demand":200},"(19, 1)":{"demand_ok":false,"compl_demand_ok":false,"has_facility":false,"compl_facility":true,"demand":100},"(19, 10)":{"demand_ok":false,"compl_demand_ok":false,"has_facility":false,"compl_facility":true,"demand":50},"(2, 3)":{"demand_ok":false,"compl_demand_ok":false,"has_facility":true,"compl_facility":true,"demand":150},"(16, 2)":{"demand_ok":false,"compl_demand_ok":false,"has_facility":true,"compl_facility":true,"demand":3350},"(6, 3)":{"demand_ok":false,"compl_demand_ok":false,"has_facility":true,"compl_facility":true,"demand":1100},"(17, 6)":{"demand_ok":false,"compl_demand_ok":false,"has_facility":false,"compl_facility":true,"demand":50},"(8, 3)":{"demand_ok":false,"compl_demand_ok":false,"has_facility":true,"compl_facility":true,"demand":1400},"(10, 0)":{"demand_ok":false,"compl_demand_ok":false,"has_facility":true,"compl_facility":true,"demand":150},"(19, 3)":{"demand_ok":false,"compl_demand_ok":false,"has_facility":true,"compl_facility":true,"demand":50},"(16, 4)":{"demand_ok":false,"compl_demand_ok":true,"has_facility":true,"compl_facility":true,"demand":3550},"(12, 0)":{"demand_ok":false,"compl_demand_ok":false,"has_facility":false,"compl_facility":true,"demand":50},"(19, 5)":{"demand_ok":false,"compl_demand_ok":false,"has_facility":true,"compl_facility":true,"demand":4200},"(10, 2)":{"demand_ok":false,"compl_demand_ok":false,"has_facility":true,"compl_facility":true,"demand":2200},"(9, 4)":{"demand_ok":false,"compl_demand_ok":false,"has_facility":false,"compl_facility":true,"demand":100},"(11, 1)":{"demand_ok":false,"compl_demand_ok":false,"has_facility":false,"compl_facility":true,"demand":50},"(0, 1)":{"demand_ok":false,"compl_demand_ok":false,"has_facility":false,"compl_facility":true,"demand":50},"(15, 1)":{"demand_ok":false,"compl_demand_ok":false,"has_facility":true,"compl_facility":true,"demand":3100},"(18, 6)":{"demand_ok":false,"compl_demand_ok":false,"has_facility":false,"compl_facility":true,"demand":100},"(12, 2)":{"demand_ok":false,"compl_demand_ok":false,"has_facility":true,"compl_facility":true,"demand":2300},"(17, 1)":{"demand_ok":false,"compl_demand_ok":false,"has_facility":true,"compl_facility":true,"demand":250},"(19, 7)":{"demand_ok":false,"compl_demand_ok":false,"has_facility":true,"compl_facility":true,"demand":4550},"(1, 1)":{"demand_ok":false,"compl_demand_ok":false,"has_facility":false,"compl_facility":true,"demand":50},"(0, 3)":{"demand_ok":false,"compl_demand_ok":false,"has_facility":true,"compl_facility":true,"demand":50},"(2, 0)":{"demand_ok":false,"compl_demand_ok":false,"has_facility":false,"compl_facility":true,"demand":250},"(15, 3)":{"demand_ok":false,"compl_demand_ok":false,"has_facility":true,"compl_facility":true,"demand":50},"(6, 0)":{"demand_ok":false,"compl_demand_ok":false,"has_facility":true,"compl_facility":true,"demand":50}},"extracted_nodes":["(12, 1)","(4, 0)","(3, 1)","(9, 2)","(8, 0)","(5, 1)","(11, 2)","(10, 0)","(8, 3)","(0, 2)","(2, 2)","(1, 0)","(1, 3)","(7, 4)","(6, 2)","(7, 1)","(12, 0)","(14, 0)","(3, 0)","(5, 0)","(8, 2)","(9, 1)","(10, 2)","(9, 4)","(11, 1)","(0, 1)","(2, 4)","(1, 2)","(2, 1)","(13, 1)","(6, 1)","(7, 0)","(7, 3)","(12, 2)","(4, 1)","(5, 2)","(9, 0)","(8, 4)","(9, 3)","(11, 0)","(8, 1)","(0, 0)","(1, 1)","(0, 3)","(10, 1)","(13, 0)","(2, 0)","(2, 3)","(7, 2)","(6, 0)","(6, 3)"]},{"label":"Phase 3: Tree Cut 2","level":"base","edges":[["(14, 1)","(14, 2)"],["(17, 0)","(17, 1)"],["(17, 3)","(16, 3)"],["(17, 3)","(18, 3)"],["(19, 0)","(18, 0)"],["(19, 6)","(18, 6)"],["(17, 6)","(18, 6)"],["(19, 3)","(19, 4)"],["(19, 3)","(19, 2)"],["(19, 9)","(19, 8)"],["(19, 9)","(18, 9)"],["(16, 4)","(17, 4)"],["(16, 4)","(16, 3)"],["(16, 4)","(16, 5)"],["(15, 2)","(16, 2)"],["(15, 2)","(15, 1)"],["(15, 2)","(14, 2)"],["(15, 2)","(15, 3)"],["(16, 1)","(17, 1)"],["(16, 1)","(16, 0)"],["(18, 4)","(18, 5)"],["(18, 1)","(17, 1)"],["(18, 1)","(18, 0)"],["(18, 1)","(19, 1)"],["(18, 7)","(18, 6)"],["(18, 7)","(19, 7)"],["(18, 10)","(18, 9)"],["(18, 10)","(19, 10)"],["(17, 2)","(16, 2)"],["(17, 2)","(17, 1)"],["(17, 5)","(18, 5)"],["(17, 5)","(17, 4)"],["(19, 2)","(18, 2)"],["(19, 5)","(18, 5)"],["(19, 5)","(19, 4)"],["(19, 8)","(19, 7)"],["(16, 3)","(16, 2)"],["(15, 1)","(15, 0)"],["(18, 6)","(18, 5)"]],"root":"(16, 2)","cut_node":"(17, 4)","psi_chosen":30.0,"psi_total":71.0,"n_cuts":3,"node_feasibility":{"(14, 1)":{"demand_ok":false,"compl_demand_ok":true,"has_facility":false,"compl_facility":true,"demand":50},"(17, 0)":{"demand_ok":false,"compl_demand_ok":true,"has_facility":false,"compl_facility":true,"demand":50},"(17, 3)":{"demand_ok":false,"compl_demand_ok":false,"has_facility":false,"compl_facility":true,"demand":100},"(19, 0)":{"demand_ok":false,"compl_demand_ok":true,"has_facility":false,"compl_facility":true,"demand":50},"(19, 6)":{"demand_ok":false,"compl_demand_ok":true,"has_facility":false,"compl_facility":true,"demand":50},"(17, 6)":{"demand_ok":false,"compl_demand_ok":true,"has_facility":false,"compl_facility":true,"demand":50},"(19, 3)":{"demand_ok":false,"compl_demand_ok":false,"has_facility":true,"compl_facility":true,"demand":150},"(19, 9)":{"demand_ok":false,"compl_demand_ok":false,"has_facility":true,"compl_facility":true,"demand":200},"(16, 4)":{"demand_ok":true,"compl_demand_ok":true,"has_facility":true,"compl_facility":true,"demand":1050},"(15, 2)":{"demand_ok":false,"compl_demand_ok":false,"has_facility":true,"compl_facility":true,"demand":300},"(16, 1)":{"demand_ok":false,"compl_demand_ok":false,"has_facility":false,"compl_facility":true,"demand":100},"(18, 4)":{"demand_ok":false,"compl_demand_ok":true,"has_facility":true,"compl_facility":true,"demand":50},"(18, 1)":{"demand_ok":false,"compl_demand_ok":false,"has_facility":true,"compl_facility":true,"demand":200},"(18, 7)":{"demand_ok":false,"compl_demand_ok":false,"has_facility":true,"compl_facility":true,"demand":350},"(18, 10)":{"demand_ok":false,"compl_demand_ok":false,"has_facility":true,"compl_facility":true,"demand":100},"(17, 2)":{"demand_ok":false,"compl_demand_ok":false,"has_facility":true,"compl_facility":true,"demand":450},"(17, 5)":{"demand_ok":false,"compl_demand_ok":false,"has_facility":true,"compl_facility":true,"demand":900},"(19, 2)":{"demand_ok":false,"compl_demand_ok":false,"has_facility":true,"compl_facility":true,"demand":100},"(19, 5)":{"demand_ok":false,"compl_demand_ok":false,"has_facility":true,"compl_facility":true,"demand":250},"(19, 8)":{"demand_ok":false,"compl_demand_ok":false,"has_facility":true,"compl_facility":true,"demand":250},"(16, 0)":{"demand_ok":false,"compl_demand_ok":true,"has_facility":false,"compl_facility":true,"demand":50},"(16, 3)":{"demand_ok":false,"compl_demand_ok":false,"has_facility":true,"compl_facility":true,"demand":1200},"(18, 0)":{"demand_ok":false,"compl_demand_ok":false,"has_facility":false,"compl_facility":true,"demand":100},"(15, 1)":{"demand_ok":false,"compl_demand_ok":false,"has_facility":true,"compl_facility":true,"demand":100},"(18, 3)":{"demand_ok":false,"compl_demand_ok":true,"has_facility":false,"compl_facility":true,"demand":50},"(18, 9)":{"demand_ok":false,"compl_demand_ok":false,"has_facility":true,"compl_facility":true,"demand":150},"(18, 6)":{"demand_ok":false,"compl_demand_ok":false,"has_facility":true,"compl_facility":true,"demand":500},"(14, 2)":{"demand_ok":false,"compl_demand_ok":false,"has_facility":false,"compl_facility":true,"demand":100},"(17, 4)":{"demand_ok":true,"compl_demand_ok":true,"has_facility":true,"compl_facility":true,"demand":950},"(17, 1)":{"demand_ok":false,"compl_demand_ok":false,"has_facility":true,"compl_facility":true,"demand":400},"(19, 4)":{"demand_ok":false,"compl_demand_ok":false,"has_facility":true,"compl_facility":true,"demand":200},"(19, 1)":{"demand_ok":false,"compl_demand_ok":true,"has_facility":false,"compl_facility":true,"demand":50},"(19, 7)":{"demand_ok":false,"compl_demand_ok":false,"has_facility":true,"compl_facility":true,"demand":300},"(19, 10)":{"demand_ok":false,"compl_demand_ok":true,"has_facility":false,"compl_facility":true,"demand":50},"(16, 2)":{"demand_ok":true,"compl_demand_ok":false,"has_facility":true,"compl_facility":true,"demand":2000},"(15, 0)":{"demand_ok":false,"compl_demand_ok":true,"has_facility":false,"compl_facility":true,"demand":50},"(16, 5)":{"demand_ok":false,"compl_demand_ok":true,"has_facility":false,"compl_facility":true,"demand":50},"(18, 2)":{"demand_ok":false,"compl_demand_ok":true,"has_facility":true,"compl_facility":true,"demand":50},"(15, 3)":{"demand_ok":false,"compl_demand_ok":true,"has_facility":true,"compl_facility":true,"demand":50},"(18, 5)":{"demand_ok":false,"compl_demand_ok":false,"has_facility":true,"compl_facility":true,"demand":850}},"extracted_nodes":["(19, 8)","(19, 6)","(18, 9)","(17, 6)","(19, 3)","(19, 9)","(18, 6)","(17, 4)","(18, 4)","(19, 4)","(18, 7)","(19, 7)","(18, 10)","(19, 10)","(18, 2)","(17, 5)","(19, 2)","(18, 5)","(19, 5)"]},{"label":"Phase 3: Tree Cut 3","level":"base","edges":[["(14, 1)","(15, 1)"],["(14, 1)","(14, 2)"],["(17, 0)","(17, 1)"],["(17, 0)","(16, 0)"],["(17, 3)","(16, 3)"],["(17, 3)","(18, 3)"],["(19, 0)","(19, 1)"],["(19, 0)","(18, 0)"],["(16, 4)","(16, 3)"],["(16, 4)","(16, 5)"],["(15, 2)","(14, 2)"],["(15, 2)","(15, 3)"],["(16, 1)","(16, 0)"],["(16, 1)","(16, 2)"],["(18, 1)","(18, 0)"],["(18, 1)","(17, 1)"],["(17, 2)","(16, 2)"],["(16, 0)","(15, 0)"],["(16, 3)","(15, 3)"],["(15, 1)","(15, 0)"]],"root":"(18, 1)","cut_node":"(18, 1)","psi_chosen":5.0,"psi_total":5.0,"n_cuts":1,"node_feasibility":{"(14, 1)":{"demand_ok":false,"compl_demand_ok":false,"has_facility":true,"compl_facility":true,"demand":450},"(17, 0)":{"demand_ok":false,"compl_demand_ok":false,"has_facility":true,"compl_facility":true,"demand":800},"(17, 3)":{"demand_ok":false,"compl_demand_ok":true,"has_facility":false,"compl_facility":true,"demand":100},"(19, 0)":{"demand_ok":false,"compl_demand_ok":true,"has_facility":false,"compl_facility":true,"demand":100},"(16, 4)":{"demand_ok":false,"compl_demand_ok":true,"has_facility":false,"compl_facility":true,"demand":100},"(15, 2)":{"demand_ok":false,"compl_demand_ok":false,"has_facility":true,"compl_facility":true,"demand":350},"(16, 1)":{"demand_ok":false,"compl_demand_ok":true,"has_facility":false,"compl_facility":true,"demand":150},"(18, 1)":{"demand_ok":true,"compl_demand_ok":false,"has_facility":true,"compl_facility":true,"demand":1050},"(17, 2)":{"demand_ok":false,"compl_demand_ok":true,"has_facility":false,"compl_facility":true,"demand":50},"(16, 0)":{"demand_ok":false,"compl_demand_ok":false,"has_facility":true,"compl_facility":true,"demand":750},"(16, 3)":{"demand_ok":false,"compl_demand_ok":false,"has_facility":false,"compl_facility":true,"demand":250},"(18, 0)":{"demand_ok":false,"compl_demand_ok":true,"has_facility":false,"compl_facility":true,"demand":150},"(15, 1)":{"demand_ok":false,"compl_demand_ok":false,"has_facility":true,"compl_facility":true,"demand":500},"(18, 3)":{"demand_ok":false,"compl_demand_ok":true,"has_facility":false,"compl_facility":true,"demand":50},"(14, 2)":{"demand_ok":false,"compl_demand_ok":false,"has_facility":true,"compl_facility":true,"demand":400},"(17, 1)":{"demand_ok":false,"compl_demand_ok":false,"has_facility":true,"compl_facility":true,"demand":850},"(19, 1)":{"demand_ok":false,"compl_demand_ok":true,"has_facility":false,"compl_facility":true,"demand":50},"(16, 2)":{"demand_ok":false,"compl_demand_ok":true,"has_facility":false,"compl_facility":true,"demand":100},"(15, 0)":{"demand_ok":false,"compl_demand_ok":false,"has_facility":true,"compl_facility":true,"demand":550},"(16, 5)":{"demand_ok":false,"compl_demand_ok":true,"has_facility":false,"compl_facility":true,"demand":50},"(15, 3)":{"demand_ok":false,"compl_demand_ok":false,"has_facility":true,"compl_facility":true,"demand":300}},"extracted_nodes":["(16, 0)","(14, 1)","(17, 0)","(16, 3)","(15, 1)","(18, 0)","(17, 3)","(19, 0)","(18, 3)","(14, 2)","(16, 4)","(15, 2)","(16, 1)","(17, 1)","(18, 1)","(19, 1)","(16, 2)","(15, 0)","(17, 2)","(16, 5)","(15, 3)"]}]},"phase4":{"label":"Phase 4: Level-1 Facility Assignment","centers":{"1":"(14, 16)","3":"(14, 19)","21":"(13, 8)","20":"(5, 18)","27":"(4, 5)","28":"(17, 1)","29":"(18, 4)","31":"(9, 15)","32":"(16, 13)","33":"(19, 14)","34":"(7, 2)","35":"(7, 11)","36":"(2, 14)"}}},"accept_reject":{"label":"Accept/Reject","energy_proposed":69700.0,"energy_current":67400.0,"accepted":true}}]